README.rst
setup.py
typora_upload/__init__.py
typora_upload/config_utils.py
typora_upload/factory.py
typora_upload/functions.py
typora_upload/init_utils.py
typora_upload/logger.py
typora_upload/main.py
typora_upload/print_utils.py
typora_upload/upload_utils.py
typora_upload.egg-info/PKG-INFO
typora_upload.egg-info/SOURCES.txt
typora_upload.egg-info/dependency_links.txt
typora_upload.egg-info/entry_points.txt
typora_upload.egg-info/requires.txt
typora_upload.egg-info/top_level.txt